bda573e80b949c0382c9__mypyc.cpython-311-x86_64-linux-musl.so
simstring/__init__.cpython-311-x86_64-linux-musl.so
simstring/__init__.py
simstring/searcher.cpython-311-x86_64-linux-musl.so
simstring/searcher.py
simstring/database/__init__.cpython-311-x86_64-linux-musl.so
simstring/database/__init__.py
simstring/database/base.py
simstring/database/dict.cpython-311-x86_64-linux-musl.so
simstring/database/dict.py
simstring/database/disk.py
simstring/feature_extractor/__init__.cpython-311-x86_64-linux-musl.so
simstring/feature_extractor/__init__.py
simstring/feature_extractor/base.cpython-311-x86_64-linux-musl.so
simstring/feature_extractor/base.py
simstring/feature_extractor/character_ngram.cpython-311-x86_64-linux-musl.so
simstring/feature_extractor/character_ngram.py
simstring/feature_extractor/word_ngram.cpython-311-x86_64-linux-musl.so
simstring/feature_extractor/word_ngram.py
simstring/measure/__init__.cpython-311-x86_64-linux-musl.so
simstring/measure/__init__.py
simstring/measure/base.cpython-311-x86_64-linux-musl.so
simstring/measure/base.py
simstring/measure/cosine.cpython-311-x86_64-linux-musl.so
simstring/measure/cosine.py
simstring/measure/dice.cpython-311-x86_64-linux-musl.so
simstring/measure/dice.py
simstring/measure/jaccard.cpython-311-x86_64-linux-musl.so
simstring/measure/jaccard.py
simstring/measure/overlap.cpython-311-x86_64-linux-musl.so
simstring/measure/overlap.py
simstring_fast-0.6.0.dist-info/METADATA
simstring_fast-0.6.0.dist-info/WHEEL
simstring_fast-0.6.0.dist-info/RECORD
simstring_fast-0.6.0.dist-info/licenses/LICENSE
