Metadata-Version: 2.4
Name: simstring-fast
Version: 0.6.0
Summary: A fork of the Python implementation of the SimString by (Katsuma Narisawa), a simple and efficient algorithm for approximate string matching. Uses mypyc to improve speed
Project-URL: Documentation, https://banking-circle-advanced-analytics.github.io/simstring-fast/
Project-URL: Issues, https://github.com/banking-circle-advanced-analytics/simstring-fast
Project-URL: Source, https://github.com/banking-circle-advanced-analytics/simstring-fast/issues
Author-email: Ruben Menke <rum@bankingcircle.com>
License-Expression: MIT
License-File: LICENSE
Classifier: Development Status :: 4 - Beta
Classifier: Programming Language :: Python
Classifier: Programming Language :: Python :: 3.10
Classifier: Programming Language :: Python :: 3.11
Classifier: Programming Language :: Python :: 3.12
Classifier: Programming Language :: Python :: 3.13
Classifier: Programming Language :: Python :: Implementation :: CPython
Requires-Python: >=3.9
Requires-Dist: diskcache==5.6.3
Requires-Dist: setuptools>=70.0.0
